pybob_sdk/__init__.py
pybob_sdk/client.py
pybob_sdk/exceptions.py
pybob_sdk/_core/__init__.py
pybob_sdk/_core/auth.py
pybob_sdk/_core/base_api.py
pybob_sdk/_core/base_model.py
pybob_sdk/_core/http.py
pybob_sdk/_core/settings.py
pybob_sdk/attendance/__init__.py
pybob_sdk/attendance/api.py
pybob_sdk/attendance/models.py
pybob_sdk/docs/__init__.py
pybob_sdk/docs/api.py
pybob_sdk/docs/models.py
pybob_sdk/employee_tables/__init__.py
pybob_sdk/employee_tables/api.py
pybob_sdk/employee_tables/models.py
pybob_sdk/goals/__init__.py
pybob_sdk/goals/api.py
pybob_sdk/goals/models.py
pybob_sdk/hiring/__init__.py
pybob_sdk/hiring/api.py
pybob_sdk/hiring/models.py
pybob_sdk/job_catalog/__init__.py
pybob_sdk/job_catalog/api.py
pybob_sdk/job_catalog/models.py
pybob_sdk/metadata/__init__.py
pybob_sdk/metadata/api.py
pybob_sdk/metadata/models.py
pybob_sdk/onboarding/__init__.py
pybob_sdk/onboarding/api.py
pybob_sdk/onboarding/models.py
pybob_sdk/people/__init__.py
pybob_sdk/people/api.py
pybob_sdk/people/models.py
pybob_sdk/reports/__init__.py
pybob_sdk/reports/api.py
pybob_sdk/reports/models.py
pybob_sdk/tasks/__init__.py
pybob_sdk/tasks/api.py
pybob_sdk/tasks/models.py
pybob_sdk/time_off/__init__.py
pybob_sdk/time_off/api.py
pybob_sdk/time_off/models.py
pybob_sdk/workforce/__init__.py
pybob_sdk/workforce/api.py
pybob_sdk/workforce/models.py
pybob_sdk-1.0.0.dist-info/METADATA
pybob_sdk-1.0.0.dist-info/WHEEL
pybob_sdk-1.0.0.dist-info/RECORD
