Metadata-Version: 2.4
Name: pybob-sdk
Version: 1.0.0
Summary: An unofficial Python SDK for the HiBob HR API
Project-URL: Homepage, https://github.com/kurtismassey/pybob
Project-URL: Documentation, https://github.com/kurtismassey/pybob#readme
Project-URL: Repository, https://github.com/kurtismassey/pybob
Author: Kurtis Massey
License: MIT
Keywords: api,async,bob,hibob,hr,pydantic,sdk
Classifier: Development Status :: 5 - Production/Stable
Classifier: Intended Audience :: Developers
Classifier: License :: OSI Approved :: MIT License
Classifier: Programming Language :: Python :: 3
Classifier: Programming Language :: Python :: 3.12
Classifier: Programming Language :: Python :: 3.13
Classifier: Typing :: Typed
Requires-Python: >=3.12
Requires-Dist: httpx<1.0,>=0.27
Requires-Dist: pydantic-settings<3.0,>=2.0
Requires-Dist: pydantic<3.0,>=2.0
Provides-Extra: dev
Requires-Dist: mypy>=1.10; extra == 'dev'
Requires-Dist: pytest-asyncio>=0.23; extra == 'dev'
Requires-Dist: pytest>=8.0; extra == 'dev'
Requires-Dist: respx>=0.21; extra == 'dev'
Requires-Dist: ruff>=0.4; extra == 'dev'
